{"collectionslug": "boredapeyachtclub", "one_day_volume": 1151.98, "one_day_change": -0.12198239086821437, "one_day_sales": 16.0, "one_day_average_price": 71.99875, "seven_day_volume": 6314.882489999998, "seven_day_change": -0.10145254208337645, "seven_day_sales": 101.0, "seven_day_average_price": 62.523589009900974, "thirty_day_volume": 30545.777613874543, "thirty_day_change": -0.3020022037156003, "thirty_day_sales": 508.0, "thirty_day_average_price": 60.12948349187902, "total_volume": 269305.6364574632, "total_sales": 23296.0, "total_supply": 10000.0, "num_owners": 5988, "average_price": 11.560166400131491, "market_cap": 625235.8900990097, "floor_price": 54.17, "external_url": "http://www.boredapeyachtclub.com/", "image_url": "https://lh3.googleusercontent.com/Ju9CkWtV-1Okvf45wo8UctR-M9He2PjILP0oOvxE89AyiPPGtrR3gysu1Zgy0hjd2xKIgjJJtWIc0ybj4Vd7wv8t3pxDGHoJBzDB=s120", "create_time": "2021-12-25_00.30.46"}